hydrate/__init__.py
hydrate-0.0.0.dist-info/METADATA
hydrate-0.0.0.dist-info/WHEEL
hydrate-0.0.0.dist-info/top_level.txt
hydrate-0.0.0.dist-info/zip-safe
hydrate-0.0.0.dist-info/RECORD
