Metadata-Version: 2.1
Name: hydrate
Version: 0.0.0
Summary: Package description here.
Home-page: UNKNOWN
Author: Niklas Rosenstein
Author-email: rosensteinniklas@gmail.com
License: UNKNOWN
Platform: UNKNOWN
Requires-Python: >=3.5.0,<4.0.0
